detametrics/__init__.py
detametrics/sdk.py
detametrics/tf.py
DetaMetrics-0.0.7.dist-info/LICENSE
DetaMetrics-0.0.7.dist-info/METADATA
DetaMetrics-0.0.7.dist-info/WHEEL
DetaMetrics-0.0.7.dist-info/top_level.txt
DetaMetrics-0.0.7.dist-info/RECORD
