Metadata-Version: 2.1
Name: DetaMetrics
Version: 0.0.7
Summary: SDK for DetaMetrics TensorBoard alternative.
Author: SamTheProgrammer
Classifier: Programming Language :: Python :: 3
Classifier: License :: OSI Approved :: MIT License
Classifier: Operating System :: OS Independent
Requires-Python: >=3.7
License-File: LICENSE
Requires-Dist: httpx (>=0.13.3)
